smpl/__init__.py
smpl/_version.py
smpl/data.py
smpl/fit.py
smpl/functions.py
smpl/interpolate.py
smpl/latex.py
smpl/plot.py
smpl/plot2d.py
smpl/stat.py
smpl/wrap.py
smpl/animation/__init__.py
smpl/animation/animation.py
smpl/debug/__init__.py
smpl/debug/debug.py
smpl/doc/__init__.py
smpl/doc/doc.py
smpl/io/__init__.py
smpl/io/cat.py
smpl/io/grep.py
smpl/io/head.py
smpl/io/io.py
smpl/io/read_buffer.py
smpl/io/sed.py
smpl/io/tail.py
smpl/parallel/__init__.py
smpl/parallel/parallel.py
smpl/util/__init__.py
smpl/util/util.py
smpl-1.5.6.dist-info/METADATA
smpl-1.5.6.dist-info/WHEEL
smpl-1.5.6.dist-info/licenses/LICENSE
smpl-1.5.6.dist-info/RECORD
