Metadata-Version: 2.4
Name: smpl
Version: 1.5.6
Summary: SiMPLe plotting and fitting
Project-URL: Documentation, https://smpl.readthedocs.io/
Project-URL: Issues, https://github.com/APN-Pucky/smpl/issues
Project-URL: Source, https://github.com/APN-Pucky/smpl
Author-email: Alexander Puck Neuwirth <alexander@neuwirth-informatik.de>
License-File: LICENSE
Classifier: Development Status :: 4 - Beta
Classifier: Intended Audience :: Developers
Classifier: Intended Audience :: Science/Research
Classifier: Programming Language :: Python
Classifier: Programming Language :: Python :: 3.9
Classifier: Programming Language :: Python :: 3.10
Classifier: Programming Language :: Python :: 3.11
Classifier: Programming Language :: Python :: 3.12
Classifier: Programming Language :: Python :: 3.13
Classifier: Programming Language :: Python :: Implementation :: CPython
Classifier: Programming Language :: Python :: Implementation :: PyPy
Classifier: Topic :: Scientific/Engineering
Requires-Python: >=3.9
Requires-Dist: deprecation
Requires-Dist: iminuit
Requires-Dist: ipywidgets
Requires-Dist: matplotlib
Requires-Dist: numpy
Requires-Dist: pandas>=1.0.0
Requires-Dist: pillow
Requires-Dist: requests
Requires-Dist: scipy>=1.7.0
Requires-Dist: smplr
Requires-Dist: sympy
Requires-Dist: tqdm
Requires-Dist: uncertainties
Provides-Extra: dev
Requires-Dist: ipython; extra == 'dev'
Requires-Dist: jupyter; extra == 'dev'
Requires-Dist: jupyterlab; extra == 'dev'
Requires-Dist: pre-commit<4.0,>=2.20; extra == 'dev'
Provides-Extra: docs
Requires-Dist: jupyter-sphinx; extra == 'docs'
Requires-Dist: myst-parser; extra == 'docs'
Requires-Dist: nbsphinx; extra == 'docs'
Requires-Dist: numpydoc; extra == 'docs'
Requires-Dist: pandoc; extra == 'docs'
Requires-Dist: sphinx-autoapi; extra == 'docs'
Requires-Dist: sphinx-autobuild; extra == 'docs'
Requires-Dist: sphinx-math-dollar; extra == 'docs'
Requires-Dist: sphinx-rtd-theme; extra == 'docs'
Requires-Dist: sphinx<8.0.0; extra == 'docs'
Requires-Dist: sphinxcontrib-napoleon; extra == 'docs'
Requires-Dist: toml; extra == 'docs'
Provides-Extra: test
Requires-Dist: nbval; extra == 'test'
Requires-Dist: pytest; extra == 'test'
Requires-Dist: pytest-cov; extra == 'test'
Requires-Dist: pytest-line-profiler-apn>=0.1.5; extra == 'test'
Requires-Dist: pytest-mpl; extra == 'test'
Requires-Dist: pytest-profiling; extra == 'test'
